filecache/__init__.py
filecache/abstract_cacher.py
filecache/deque_cache.py
filecache/exceptions.py
filecache/file_cacher.py
filecache/function_cacher.py
filecache/invalidation_dict.py
filecache/json_cacher.py
filecache/mixin/__init__.py
filecache/mixin/abstract_cache_comparison.py
filecache/shelve_cacher.py
filecache/typing.py
filecache/utils/__init__.py
filecache/utils/compare.py
filecache/utils/inspect.py
filecache/utils/path.py
filecache/utils/shelve.py
filecache/utils/string.py
filecacheutils-0.1.0.post1.dist-info/METADATA
filecacheutils-0.1.0.post1.dist-info/WHEEL
filecacheutils-0.1.0.post1.dist-info/entry_points.txt
filecacheutils-0.1.0.post1.dist-info/licenses/LICENSE
filecacheutils-0.1.0.post1.dist-info/RECORD
