Metadata-Version: 2.1
Name: filecacheutils
Version: 0.1.0.post1
Summary: Various caching utilities
Author-Email: Topi Aaltonen <aaltopi@gmail.com>
License: MIT
Project-URL: source, https://github.com/aaltop/filecache
Project-URL: issues, https://github.com/aaltop/filecache/issues
Requires-Python: <3.14,>=3.12
